lazyemployee
